fin_data/__init__.py
fin_data/blacklist.py
fin_data/database/__init__.py
fin_data/database/compare.py
fin_data/database/create.py
fin_data/database/engine.py
fin_data/database/load.py
fin_data/database/load_sources.py
fin_data/database/tests/__init__.py
fin_data/database/tests/conftest.py
fin_data/database/tests/main.py
fin_data/database/tests/test_compare.py
fin_data/database/tests/test_data_id_creator.py
fin_data/database/tests/test_filters.py
fin_data/database/tests/test_load.py
fin_data/database/tests/test_load_sources.py
fin_data/database/types.py
fin_data/database/utils.py
fin_data/export/__init__.py
fin_data/export/export.py
fin_data/export/tables.py
fin_data/export/tests/test_export.py
fin_data/export/utils.py
fin_data/models/__init__.py
fin_data/models/company.py
fin_data/models/options.py
fin_data/queries/__init__.py
fin_data/queries/quotes.py
fin_data/queries/symbols.py
fin_data/s3.py
fin_data/tools/__init__.py
fin_data/tools/add_symbols.py
fin_data/transform/__init__.py
fin_data/transform/clean_company_info.py
fin_data/transform/combine_company_info.py
fin_data/transform/data/ISO10383_MIC.csv
fin_data/transform/data/README.md
fin_data/transform/data/__init__.py
fin_data/transform/data/countries.py
fin_data/transform/data/states.py
fin_data/transform/exchanges.py
fin_data/utils.py
fin_data-0.5.3.dist-info/WHEEL
fin_data-0.5.3.dist-info/METADATA
fin_data-0.5.3.dist-info/RECORD
