Metadata-Version: 2.1
Name: fin-data
Version: 0.5.3
Summary: 
Author: Dan Kelleher
Author-email: kelleherjdan@gmail.com
Requires-Python: >=3.9,<4.0
Classifier: Programming Language :: Python :: 3
Classifier: Programming Language :: Python :: 3.10
Classifier: Programming Language :: Python :: 3.9
Provides-Extra: export
Requires-Dist: SQLAlchemy (>=1.4.28,<2.0.0)
Requires-Dist: asyncpg (>=0.25.0,<0.26.0)
Requires-Dist: boto3 (==1.21.0); extra == "export"
Requires-Dist: cytoolz (>=0.11.2,<0.12.0)
Requires-Dist: pandas (>=1.4.2,<2.0.0); extra == "export"
Requires-Dist: psycopg[c] (>=3.0.15,<4.0.0)
Requires-Dist: pyarrow (>=8.0.0,<9.0.0); extra == "export"
Requires-Dist: pydantic (>=1.9.1,<2.0.0)
Requires-Dist: ready-logger (>=0.1.0,<0.2.0)
Requires-Dist: s3fs (>=2022.5.0,<2023.0.0); extra == "export"
Requires-Dist: sh (>=1.14.2,<2.0.0)
